forestry/__init__.py
forestry/trees.py
forestry-0.0.2.dist-info/LICENSE
forestry-0.0.2.dist-info/METADATA
forestry-0.0.2.dist-info/WHEEL
forestry-0.0.2.dist-info/top_level.txt
forestry-0.0.2.dist-info/RECORD
