Metadata-Version: 2.1
Name: forestry
Version: 0.0.2
Summary: Python Tree data structures and tools.
Home-page: https://github.com/dwightdc/forestry
Author: Dwight D. Cummings
Author-email: dwight.cummings@yahoo.com
License: MIT
Platform: UNKNOWN
Classifier: Programming Language :: Python :: 3.7
